worstpassword.py
worstpassword-0.1.1.dist-info/LICENSE
worstpassword-0.1.1.dist-info/METADATA
worstpassword-0.1.1.dist-info/WHEEL
worstpassword-0.1.1.dist-info/entry_points.txt
worstpassword-0.1.1.dist-info/RECORD
